moudle/__init__.py
moudle/core.py
cc_package-0.0.1.dist-info/LICENSE
cc_package-0.0.1.dist-info/METADATA
cc_package-0.0.1.dist-info/WHEEL
cc_package-0.0.1.dist-info/top_level.txt
cc_package-0.0.1.dist-info/RECORD
